market_gpt/ChatGPT.py
market_gpt/__init__.py
market_gpt/__main__.py
market_gpt/prompt.py
market_gpt/tests/__init__.py
market_gpt-0.3.6.dist-info/LICENSE
market_gpt-0.3.6.dist-info/METADATA
market_gpt-0.3.6.dist-info/WHEEL
market_gpt-0.3.6.dist-info/entry_points.txt
market_gpt-0.3.6.dist-info/top_level.txt
market_gpt-0.3.6.dist-info/zip-safe
market_gpt-0.3.6.dist-info/RECORD
