Metadata-Version: 2.1
Name: market-gpt
Version: 0.3.6
Summary: Get market sentiment score with the assistance of OpenAI GPT-3.
Home-page: https://github.com/NeroCube/market-gpt
Author: Nero Chen
Author-email: nerocube.tw@gmail.com
Project-URL: Bug Tracker, https://github.com/NeroCube/market-gpt/issues
Classifier: Programming Language :: Python :: 3
Classifier: License :: OSI Approved :: MIT License
Classifier: Operating System :: OS Independent
Requires-Python: >=3.7.1
License-File: LICENSE
Requires-Dist: openai (>=0.26.1)
